{"theme": {"theme": "pesterchum2.5"}, "interface": {"blink_taskbar_on_memos": false, "minimize": 0, "tabbed_conversations": true, "close": 0, "blink_taskbar_on_pesters": false, "tabbed_memos": true}, "conversations": {"clock_type": 1, "show_seconds": false, "time_stamps": true, "use_animated_smilies": false, "op_and_voice_in_memos": false, "receive_random_encounters": false}, "chum_list": {"hide_offline_chums": false, "sort_chums": 0, "low_bandwidth": false, "show_empty_groups": false, "show_number_of_online_chums": false}}